oocd_tool/__init__.py
oocd_tool/_credentials.py
oocd_tool/configs.py
oocd_tool/main.py
oocd_tool/openocd_pb2.py
oocd_tool/openocd_pb2_grpc.py
oocd_tool/process.py
oocd_tool/rpc_client.py
oocd_tool/rpc_impl.py
oocd_tool/rpc_server.py
oocd_tool/credentials/localhost.crt
oocd_tool/credentials/localhost.key
oocd_tool/credentials/root.crt
oocd_tool-0.2.0.data/scripts/oocd-rpcd
oocd_tool-0.2.0.data/scripts/oocd-tool
oocd_tool-0.2.0.dist-info/LICENSE
oocd_tool-0.2.0.dist-info/METADATA
oocd_tool-0.2.0.dist-info/WHEEL
oocd_tool-0.2.0.dist-info/entry_points.txt
oocd_tool-0.2.0.dist-info/top_level.txt
oocd_tool-0.2.0.dist-info/RECORD
