Metadata-Version: 2.1
Name: oocd-tool
Version: 0.2.0
Summary: A flexible configuration and remote contol tool for openocd.
Home-page: https://github.com/jasa/oocd-tool.git
Author: Jacob Schultz Andersen
Author-email: schultz.jacob@gmail.com
License: UNKNOWN
Project-URL: Bug Tracker, https://github.com/jasa/oocd-tool/issues
Keywords: arm gdb cortex cortex-m trace microcontroller
Platform: UNKNOWN
Classifier: Programming Language :: Python :: 3
Classifier: License :: OSI Approved :: Mozilla Public License 2.0 (MPL 2.0)
Classifier: Operating System :: OS Independent
Requires-Python: >=3.6
License-File: LICENSE
Requires-Dist: setuptools (>=42)
Requires-Dist: psutil (>=5)
Requires-Dist: grpcio (>=1.41)
Requires-Dist: grpcio-tools (>=1.41)
